knitro/__init__.py
knitro/constants.py
knitro/knitro.py
knitro/wrapper.py
knitro/include/knitro.h
knitro/knitroampl/knitroampl.exe
knitro/lib/knitro.dll
knitro/lib/libiomp5md.dll
knitro/numpy/__init__.py
knitro/numpy/knitroNumPy.py
knitro/scipy/__init__.py
knitro/scipy/scipy_wrapper.py
knitro-15.1.0.dist-info/LICENSE
knitro-15.1.0.dist-info/METADATA
knitro-15.1.0.dist-info/WHEEL
knitro-15.1.0.dist-info/top_level.txt
knitro-15.1.0.dist-info/RECORD
