Metadata-Version: 2.1
Name: knitro
Version: 15.1.0
Summary: Python interface to the nonlinear programming solver Artelys Knitro
Author-email: Artelys <info-knitro@artelys.com>
Maintainer-email: Artelys <info-knitro@artelys.com>
License: End-User License Agreement for Artelys Knitro(R)
Project-URL: Homepage, https://www.artelys.com/solvers/knitro/
Project-URL: Download, https://www.artelys.com/solvers/knitro/
Project-URL: Support and Bug Reports, https://groups.google.com/g/knitro
Keywords: optimization,nonlinear optimization,convex optimization,non-convex optimization,black-box optimization,derivative-free optimization,nlp,minlp,mathematical programming,nonlinear programming,quadratic programming,operations research,solver
Classifier: Development Status :: 5 - Production/Stable
Classifier: Intended Audience :: Developers
Classifier: Intended Audience :: Information Technology
Classifier: Intended Audience :: Science/Research
Classifier: Topic :: Scientific/Engineering
Classifier: Topic :: Scientific/Engineering :: Mathematics
Classifier: Topic :: Software Development :: Libraries :: Python Modules
Classifier: Programming Language :: Python :: 3
Classifier: Programming Language :: Python
Classifier: Programming Language :: C++
Classifier: Programming Language :: C
Classifier: Programming Language :: C#
Classifier: Programming Language :: Java
Classifier: Programming Language :: Fortran
Classifier: Programming Language :: R
Requires-Python: >=3.6
License-File: LICENSE
